drafts/TestJSON/TestJSON.py
src/temperature_monitoring_mqtt_sldewit/__init__.py
src/temperature_monitoring_mqtt_sldewit/temperature_monitor_mqtt.py
temperaturemonitor_mqtt_sldewit-1.0.0.dist-info/METADATA
temperaturemonitor_mqtt_sldewit-1.0.0.dist-info/WHEEL
temperaturemonitor_mqtt_sldewit-1.0.0.dist-info/licenses/LICENSE
temperaturemonitor_mqtt_sldewit-1.0.0.dist-info/RECORD
