Metadata-Version: 2.1
Name: TemperatureMonitor_MQTT_sldewit
Version: 1.0.0
Summary: Temperature Monitoring system using MQTT
Project-URL: Homepage, https://github.com/sldewit/TemperatureMonitor_MQTT
Project-URL: Bug Tracker, https://github.com/sldewit/TemperatureMonitor_MQTT/issues
Author-email: Stephan de Wit <stephan@de-wit.me>
License-File: LICENSE
Classifier: License :: OSI Approved :: MIT License
Classifier: Operating System :: OS Independent
Classifier: Programming Language :: Python :: 3
Requires-Python: >=3.7
Requires-Dist: paho-mqtt==1.6.1
Requires-Dist: pi1wire==0.3.0
